qute_prueba_libreria/Funciones.py
qute_prueba_libreria/__init__.py
qute_prueba_libreria-0.0.1.dist-info/METADATA
qute_prueba_libreria-0.0.1.dist-info/WHEEL
qute_prueba_libreria-0.0.1.dist-info/top_level.txt
qute_prueba_libreria-0.0.1.dist-info/RECORD
