Metadata-Version: 2.1
Name: qute_prueba_libreria
Version: 0.0.1
Summary: Librería para resolver la ecuación de schrodinger y obtener valores esperados
Home-page: 
Author: David
Author-email: david.chura@usach.cl
License: MIT
Requires-Dist: numpy
Requires-Dist: scipy
